packetizer/__init__.py
packetizer/__main__.py
packetizer/ast_utils.py
packetizer/class_extractor.py
packetizer/packetizer.py
packetizer/utils.py
packetizer/writers.py
packetizer-0.1.8.dist-info/METADATA
packetizer-0.1.8.dist-info/WHEEL
packetizer-0.1.8.dist-info/entry_points.txt
packetizer-0.1.8.dist-info/RECORD
