Metadata-Version: 2.1
Name: packetizer
Version: 0.1.8
Summary: 
Author: Uriel Reina
Author-email: urielreina@gmail.com
Requires-Python: >=3.9,<4.0
Classifier: Programming Language :: Python :: 3
Classifier: Programming Language :: Python :: 3.9
Classifier: Programming Language :: Python :: 3.10
Classifier: Programming Language :: Python :: 3.11
Requires-Dist: typer (>=0.9.0,<0.10.0)
